<?xml version="1.0" encoding="utf-8" standalone="yes"?>
<carrier_config_list>
<carrier_config mcc="222" mnc="88">
    <string name="carrier_config_version_string">windtre_it-32000000577.48</string>
    <string-array name="carrier_certificate_string_array" num="3">
        <item value="7A6D2E2EDEA23A93FA95A447535675CFB543919698196FB720B1520658D25DC7" />
        <item value="A69A419CFB5FB8344D2AEDCED6BC2A7FCB74F85161BCA9265C54E95E478839C3" />
        <item value="998DA7CED0E1A3A14E51FAEF1F8608A494BDA791B6609A1C5E599F9B64F01674" />
    </string-array>
    <boolean name="carrier_supports_ss_over_ut_bool" value="true" />
    <int name="carrier_ussd_method_int" value="2" />
    <boolean name="carrier_volte_available_bool" value="true" />
    <string name="default_vm_number_string">4200</string>
    <boolean name="show_4g_for_lte_data_icon_bool" value="true" />
</carrier_config>
<carrier_config mcc="222" mnc="88" gid1="00000099">
    <string name="carrier_config_version_string">verymobile_it-32000000577.48</string>
    <string-array name="carrier_certificate_string_array" num="3">
        <item value="7A6D2E2EDEA23A93FA95A447535675CFB543919698196FB720B1520658D25DC7" />
        <item value="A69A419CFB5FB8344D2AEDCED6BC2A7FCB74F85161BCA9265C54E95E478839C3" />
        <item value="998DA7CED0E1A3A14E51FAEF1F8608A494BDA791B6609A1C5E599F9B64F01674" />
    </string-array>
    <boolean name="carrier_supports_ss_over_ut_bool" value="true" />
    <int name="carrier_ussd_method_int" value="2" />
    <boolean name="carrier_volte_available_bool" value="true" />
    <string name="default_vm_number_string">4200</string>
    <boolean name="show_4g_for_lte_data_icon_bool" value="true" />
</carrier_config>
</carrier_config_list>
